uc_tools/__about__.py
uc_tools/__init__.py
uc_tools/config/__init__.py
uc_tools/config/env.py
uc_tools/http_server/__init__.py
uc_tools/http_server/routes.py
uc_tools/http_server/server.py
uc_tools/logger/__init__.py
uc_tools/redis/__init__.py
uc_tools/redis/redis.py
uc_tools/tools/__init__.py
uc_tools/tools/decode.py
uc_tools/tools/retry.py
python_uc_tools-0.2.0.dist-info/METADATA
python_uc_tools-0.2.0.dist-info/WHEEL
python_uc_tools-0.2.0.dist-info/licenses/LICENSE.txt
python_uc_tools-0.2.0.dist-info/RECORD
